MANIFEST.in
VERSION
requirements.txt
setup.cfg
setup.py
avroschemaserializer/__init__.py
avroschemaserializer.egg-info/PKG-INFO
avroschemaserializer.egg-info/SOURCES.txt
avroschemaserializer.egg-info/dependency_links.txt
avroschemaserializer.egg-info/requires.txt
avroschemaserializer.egg-info/top_level.txt
avroschemaserializer/schemaregistry/__init__.py
avroschemaserializer/schemaregistry/client/ClientError.py
avroschemaserializer/schemaregistry/client/SchemaRegistryClient.py
avroschemaserializer/schemaregistry/client/__init__.py
avroschemaserializer/schemaregistry/serializers/MessageSerializer.py
avroschemaserializer/schemaregistry/serializers/Util.py
avroschemaserializer/schemaregistry/serializers/__init__.py
avroschemaserializer/schemaregistry/tests/__init__.py
avroschemaserializer/schemaregistry/tests/adv_schema.avsc
avroschemaserializer/schemaregistry/tests/basic_schema.avsc
avroschemaserializer/schemaregistry/tests/data_gen.py
avroschemaserializer/schemaregistry/tests/mock_registry.py
avroschemaserializer/schemaregistry/tests/test_cached_client.py
avroschemaserializer/schemaregistry/tests/test_message_serializer.py
avroschemaserializer/schemaregistry/tests/test_registry.py
avroschemaserializer/schemaregistry/tests/test_util.py